jwst_backgrounds/__init__.py
jwst_backgrounds/cli.py
jwst_backgrounds/docopt.py
jwst_backgrounds/jbt.py
jwst_backgrounds/version.py
jwst_backgrounds/agreement/NASA_Open_Source_Agreement_1.3 GSC-17919.pdf
jwst_backgrounds/refdata/std_spectrum_wavelengths.txt
jwst_backgrounds/refdata/thermal_curve_jwst_jrigby_1.0.csv
jwst_backgrounds/refdata/thermal_curve_jwst_jrigby_cchen_1.1a.csv
jwst_backgrounds/refdata/thermal_curve_jwst_jrigby_v2.2.csv
jwst_backgrounds/refdata/thermal_curve_jwst_jrigby_v3.0.csv
jwst_backgrounds/refdata/thermal_curve_jwst_jrigby_v4.0.csv
jwst_backgrounds-1.3.0.dist-info/LICENSE.rst
jwst_backgrounds-1.3.0.dist-info/METADATA
jwst_backgrounds-1.3.0.dist-info/WHEEL
jwst_backgrounds-1.3.0.dist-info/entry_points.txt
jwst_backgrounds-1.3.0.dist-info/top_level.txt
jwst_backgrounds-1.3.0.dist-info/RECORD
