Metadata-Version: 2.1
Name: jwst_backgrounds
Version: 1.3.0
Summary: Retrieve and plot JWST background information
Home-page: https://github.com/spacetelescope/jwst_background
Download-URL: https://github.com/spacetelescope/jwst_backgrounds/
Author: Jane Rigby (GSFC) and Klaus Pontoppidan (STScI)
Author-email: Jane.Rigby@nasa.gov
License: BSD
License-File: LICENSE.rst
Requires-Dist: healpy >=1.10
Requires-Dist: matplotlib >=3.1.1
Requires-Dist: numpy >=1.17.0
Requires-Dist: scipy >=1.1.0
